{
  "stats": {
    "suites": 1,
    "tests": 1,
    "passes": 1,
    "pending": 0,
    "failures": 0,
    "start": "2021-04-03T04:38:06.173Z",
    "end": "2021-04-03T04:38:06.440Z",
    "duration": 267
  },
  "tests": [
    {
      "title": "exists",
      "fullTitle": "index.js exists",
      "duration": 1,
      "currentRetry": 0,
      "err": {}
    }
  ],
  "pending": [],
  "failures": [],
  "passes": [
    {
      "title": "exists",
      "fullTitle": "index.js exists",
      "duration": 1,
      "currentRetry": 0,
      "err": {}
    }
  ]
}